pythi/__init__.py
pythi/downloader.py
pythi/pythi.py
pythi-0.0.3.dist-info/LICENSE
pythi-0.0.3.dist-info/METADATA
pythi-0.0.3.dist-info/WHEEL
pythi-0.0.3.dist-info/top_level.txt
pythi-0.0.3.dist-info/RECORD
