Metadata-Version: 2.1
Name: pythi
Version: 0.0.3
Summary: A minimal Python package for important helpers in python/jupyter projects.
Home-page: https://github.com/phyti1/pythi
Author: Pascal Berger
Author-email: phyti1phyti1@gmail.com
License: MIT
License-File: LICENSE
